[
    {
        "name": "Churrasco Técnico",
        "uni": "IST",
        "data": "28/07/2024",
        "hora": "18:00",
        "preco_J": 1.2,
        "preco_S": 2.5
    },

    {
        "name": "Arraial TAISCTE",
        "uni": "ISCTE",
        "data": "29/07/2024",
        "hora": "12000",
        "preco_J": 0.5,
        "preco_S": 1.0
    }
    ,

    {
        "name": "Arraial TAISCTE",
        "uni": "ISCTE",
        "data": "29/07/2024",
        "hora": "12000",
        "preco_J": 0.5,
        "preco_S": 1.0
    }
    ,

    {
        "name": "Arraial TAISCTE",
        "uni": "ISCTE",
        "data": "29/07/2024",
        "hora": "12000",
        "preco_J": 0.5,
        "preco_S": 1.0
    }
]